{
    "config": {
        "ble": {
            "enable": false,
            "rpc": {
                "enable": false
            },
            "observer": {
                "enable": false
            }
        },
        "cloud": {
            "enable": true,
            "server": "shelly-9-eu.shelly.cloud:6022/jrpc"
        },
        "em:0": {
            "id": 0,
            "name": "Energy Monitor Test Name 0",
            "blink_mode_selector": "active_energy",
            "phase_selector": "all",
            "monitor_phase_sequence": false,
            "reverse": {}
        },
        "emdata:0": {},
        "eth": {
            "enable": true,
            "ipv4mode": "dhcp",
            "ip": null,
            "netmask": null,
            "gw": null,
            "nameserver": null
        },
        "modbus": {
            "enable": true
        },
        "mqtt": {
            "enable": false,
            "server": null,
            "client_id": "shellypro3em-aabbccddeeff",
            "user": null,
            "ssl_ca": null,
            "topic_prefix": "shellypro3em-aabbccddeeff",
            "rpc_ntf": true,
            "status_ntf": false,
            "use_client_cert": false,
            "enable_rpc": true,
            "enable_control": true
        },
        "sys": {
            "device": {
                "name": "Test Name",
                "mac": "AABBCCDDEEFF",
                "fw_id": "20231219-134001/1.1.0-g34b5d4f",
                "discoverable": true,
                "eco_mode": true,
                "profile": "triphase",
                "addon_type": null
            },
            "location": {
                "tz": "Europe/Rome",
                "lat": 45.45803,
                "lon": 7.87121
            },
            "debug": {
                "level": 2,
                "file_level": null,
                "mqtt": {
                    "enable": false
                },
                "websocket": {
                    "enable": false
                },
                "udp": {
                    "addr": null
                }
            },
            "ui_data": {},
            "rpc_udp": {
                "dst_addr": null,
                "listen_port": null
            },
            "sntp": {
                "server": "192.168.1.10"
            },
            "cfg_rev": 29
        },
        "temperature:0": {
            "id": 0,
            "name": null,
            "report_thr_C": 5.0,
            "offset_C": 0.0
        },
        "wifi": "Wifi-Network-Name",
        "ws": {
            "enable": false,
            "server": "ws://192.168.1.10:8123/api/shelly/ws",
            "ssl_ca": "*"
        }
    },
    "shelly": {
        "name": "Test Name",
        "id": "shellypro3em-aabbccddeeff",
        "mac": "AABBCCDDEEFF",
        "slot": 0,
        "model": "SPEM-003CEBEU",
        "gen": 2,
        "fw_id": "20231219-134001/1.1.0-g34b5d4f",
        "ver": "1.1.0",
        "app": "Pro3EM",
        "auth_en": false,
        "auth_domain": null,
        "profile": "triphase"
    },
    "status": {
        "ble": {},
        "cloud": {
            "connected": true
        },
        "em:0": {
            "id": 0,
            "a_current": 10.965,
            "a_voltage": 223.6,
            "a_act_power": 2367.6,
            "a_aprt_power": 2450.9,
            "a_pf": 0.98,
            "a_freq": 50.0,
            "b_current": 0.966,
            "b_voltage": 223.7,
            "b_act_power": 149.7,
            "b_aprt_power": 216.0,
            "b_pf": 0.77,
            "b_freq": 50.0,
            "c_current": 0.422,
            "c_voltage": 223.8,
            "c_act_power": 13.7,
            "c_aprt_power": 94.3,
            "c_pf": 0.54,
            "c_freq": 50.0,
            "n_current": null,
            "total_current": 12.354,
            "total_act_power": 2530.977,
            "total_aprt_power": 2761.177,
            "user_calibrated_phase": []
        },
        "emdata:0": {
            "id": 0,
            "a_total_act_energy": 2031637.32,
            "a_total_act_ret_energy": 0.0,
            "b_total_act_energy": 184947.57,
            "b_total_act_ret_energy": 40.7,
            "c_total_act_energy": 369411.29,
            "c_total_act_ret_energy": 985.91,
            "total_act": 2585996.18,
            "total_act_ret": 1026.61
        },
        "eth": {
            "ip": "192.168.1.105"
        },
        "modbus": {},
        "mqtt": {
            "connected": false
        },
        "sys": {
            "mac": "AABBCCDDEEFF",
            "restart_required": false,
            "time": "13:53",
            "unixtime": 1707310438,
            "uptime": 2069125,
            "ram_size": 241516,
            "ram_free": 123528,
            "fs_size": 524288,
            "fs_free": 184320,
            "cfg_rev": 29,
            "kvs_rev": 0,
            "schedule_rev": 0,
            "webhook_rev": 0,
            "available_updates": {
                "beta": {
                    "version": "1.2.0-beta1"
                }
            },
            "reset_reason": 1
        },
        "temperature:0": {
            "id": 0,
            "tC": 46.1,
            "tF": 115.0
        },
        "wifi": {
            "sta_ip": null,
            "status": "disconnected",
            "ssid": null,
            "rssi": 0
        },
        "ws": {
            "connected": false
        }
    }
}
